form_util/__init__.py
form_util/apps.py
form_util/forms.py
form_util/urls.py
form_util/views.py
form_util/migrations/__init__.py
form_util/models/__init__.py
form_util/static/form_util/style.css
form_util/templates/form_util/index.html
form_util-0.5.7.dist-info/licenses/LICENSE
form_util-0.5.7.dist-info/METADATA
form_util-0.5.7.dist-info/WHEEL
form_util-0.5.7.dist-info/entry_points.txt
form_util-0.5.7.dist-info/top_level.txt
form_util-0.5.7.dist-info/RECORD
